langchain_europe_pmc/__init__.py
langchain_europe_pmc/py.typed
langchain_europe_pmc/retrievers.py
langchain_europe_pmc/utils.py
langchain_europe_pmc-0.1.0.dist-info/LICENSE
langchain_europe_pmc-0.1.0.dist-info/METADATA
langchain_europe_pmc-0.1.0.dist-info/WHEEL
langchain_europe_pmc-0.1.0.dist-info/RECORD
